dnfunc/__init__.py
dnfunc/dnfunc.py
dnfunc-0.2.0.dist-info/METADATA
dnfunc-0.2.0.dist-info/WHEEL
dnfunc-0.2.0.dist-info/licenses/LICENSE
dnfunc-0.2.0.dist-info/RECORD
