Metadata-Version: 2.4
Name: dnfunc
Version: 0.2.0
Summary: A collection of Vapoursynth functions and wrappers
Project-URL: Repository, https://github.com/deadnews/dnfunc
Project-URL: Changelog, https://github.com/deadnews/dnfunc/CHANGELOG.md
Author-email: deadnews <deadnewsgit@gmail.com>
License-Expression: MIT
License-File: LICENSE
Keywords: vapoursynth,vapoursynth-functions,video-encoding
Classifier: Operating System :: OS Independent
Classifier: Topic :: Multimedia :: Video
Requires-Python: >=3.13
Requires-Dist: havsfunc>=33
Requires-Dist: lvsfunc>=0.8.0
Requires-Dist: pyyaml>=6.0.2
Requires-Dist: vapoursynth>=72
Requires-Dist: vstools>=3.3.3
Requires-Dist: vsutil>=0.8.0
